dffml_model_autosklearn/__init__.py
dffml_model_autosklearn/autoclassifier.py
dffml_model_autosklearn/autoregressor.py
dffml_model_autosklearn/config.py
dffml_model_autosklearn/version.py
tests/__init__.py
tests/test_autoclassifier_integration.py
tests/test_models.py
dffml_model_autosklearn-0.1.0.post0.dist-info/LICENSE
dffml_model_autosklearn-0.1.0.post0.dist-info/METADATA
dffml_model_autosklearn-0.1.0.post0.dist-info/WHEEL
dffml_model_autosklearn-0.1.0.post0.dist-info/entry_points.txt
dffml_model_autosklearn-0.1.0.post0.dist-info/top_level.txt
dffml_model_autosklearn-0.1.0.post0.dist-info/RECORD
